cognite_jupyterlab_theme/__init__.py
cognite_jupyterlab_theme/_version.py
cognite_jupyterlab_theme-3.5.7.data/data/share/jupyter/labextensions/cognite_jupyterlab_theme/package.json
cognite_jupyterlab_theme-3.5.7.data/data/share/jupyter/labextensions/cognite_jupyterlab_theme/static/568.8c4e331c19ed964a6f34.js
cognite_jupyterlab_theme-3.5.7.data/data/share/jupyter/labextensions/cognite_jupyterlab_theme/static/remoteEntry.188527e840d362e7a04c.js
cognite_jupyterlab_theme-3.5.7.data/data/share/jupyter/labextensions/cognite_jupyterlab_theme/static/style.js
cognite_jupyterlab_theme-3.5.7.data/data/share/jupyter/labextensions/cognite_jupyterlab_theme/static/third-party-licenses.json
cognite_jupyterlab_theme-3.5.7.data/data/share/jupyter/labextensions/cognite_jupyterlab_theme/themes/cognite_jupyterlab_theme/index.css
cognite_jupyterlab_theme-3.5.7.data/data/share/jupyter/labextensions/cognite_jupyterlab_theme/themes/cognite_jupyterlab_theme/index.js
cognite_jupyterlab_theme-3.5.7.data/data/share/jupyter/labextensions/cognite_jupyterlab_theme/install.json
cognite_jupyterlab_theme-3.5.7.dist-info/METADATA
cognite_jupyterlab_theme-3.5.7.dist-info/WHEEL
cognite_jupyterlab_theme-3.5.7.dist-info/licenses/LICENSE
cognite_jupyterlab_theme-3.5.7.dist-info/RECORD
