Metadata-Version: 2.1
Name: cognite_jupyterlab_theme
Version: 3.5.7
Summary: A JupyterLab extension.
Project-URL: Homepage, https://github.com/cognitedata/cognite-jupyterlab-theme
Project-URL: Bug Tracker, https://github.com/cognitedata/cognite-jupyterlab-theme/issues
Project-URL: Repository, https://github.com/cognitedata/cognite-jupyterlab-theme.git
License: BSD 3-Clause License
License-File: LICENSE
Classifier: Framework :: Jupyter
Classifier: Framework :: Jupyter :: JupyterLab
Classifier: Framework :: Jupyter :: JupyterLab :: 3
Classifier: Framework :: Jupyter :: JupyterLab :: Extensions
Classifier: Framework :: Jupyter :: JupyterLab :: Extensions :: Prebuilt
Classifier: License :: OSI Approved :: BSD License
Classifier: Programming Language :: Python
Classifier: Programming Language :: Python :: 3
Classifier: Programming Language :: Python :: 3.8
Classifier: Programming Language :: Python :: 3.9
Classifier: Programming Language :: Python :: 3.10
Classifier: Programming Language :: Python :: 3.11
Requires-Python: >=3.8
